ifermi/__init__.py
ifermi/_version.py
ifermi/analysis.py
ifermi/boltztrap.py
ifermi/brillouin_zone.py
ifermi/cli.py
ifermi/defaults.py
ifermi/interpolate.py
ifermi/kpoints.py
ifermi/plot.py
ifermi/slice.py
ifermi/surface.py
ifermi-0.3.6.dist-info/LICENSE
ifermi-0.3.6.dist-info/METADATA
ifermi-0.3.6.dist-info/WHEEL
ifermi-0.3.6.dist-info/entry_points.txt
ifermi-0.3.6.dist-info/top_level.txt
ifermi-0.3.6.dist-info/RECORD
