Metadata-Version: 2.1
Name: ifermi
Version: 0.3.6
Summary: Fermi surface plotting tool from DFT output
Author-email: Amy Searle <amyjadesearle@gmail.com>
License: MIT
Project-URL: homepage, https://fermisurfaces.github.io/IFermi/
Project-URL: repository, https://github.com/fermisurfaces/IFermi
Project-URL: documentation, https://fermisurfaces.github.io/IFermi/
Project-URL: changelog, https://github.com/fermisurfaces/IFermi/blob/main/CHANGELOG.md
Keywords: fermi-surface,pymatgen,dft,vasp,band,materials-science
Classifier: Development Status :: 5 - Production/Stable
Classifier: Topic :: Scientific/Engineering :: Chemistry
Classifier: Topic :: Scientific/Engineering :: Physics
Classifier: Topic :: Scientific/Engineering
Classifier: License :: OSI Approved :: MIT License
Classifier: Operating System :: OS Independent
Classifier: Programming Language :: Python :: 3
Classifier: Programming Language :: Python :: 3.11
Classifier: Programming Language :: Python :: 3.10
Classifier: Programming Language :: Python :: 3.9
Classifier: Topic :: Other/Nonlisted Topic
Classifier: Topic :: Scientific/Engineering
Requires-Python: >=3.9
License-File: LICENSE
Requires-Dist: numpy
Requires-Dist: scipy
Requires-Dist: matplotlib
Requires-Dist: pymatgen>=2017.12.30
Requires-Dist: BoltzTraP2
Requires-Dist: trimesh
Requires-Dist: meshcut
Requires-Dist: scikit-image
Requires-Dist: monty
Requires-Dist: spglib
Requires-Dist: plotly
Requires-Dist: pyfftw
Requires-Dist: psutil
Requires-Dist: click
Requires-Dist: networkx
Requires-Dist: tabulate
Provides-Extra: crystal-toolkit
Requires-Dist: crystal-toolkit; extra == "crystal-toolkit"
Provides-Extra: decimation
Requires-Dist: open3d; extra == "decimation"
Provides-Extra: dev
Requires-Dist: pre-commit>=2.12.1; extra == "dev"
Provides-Extra: docs
Requires-Dist: sphinx==8.0.2; extra == "docs"
Requires-Dist: sphinx-click==6.0.0; extra == "docs"
Requires-Dist: furo==2024.8.6; extra == "docs"
Requires-Dist: sphinx-autodoc-typehints==2.3.0; extra == "docs"
Requires-Dist: myst-parser==4.0.0; extra == "docs"
Requires-Dist: nbsphinx==0.9.5; extra == "docs"
Requires-Dist: nbsphinx-link==1.3.0; extra == "docs"
Requires-Dist: ipython==8.27.0; extra == "docs"
Requires-Dist: docutils==0.20.1; extra == "docs"
Provides-Extra: mayavi
Requires-Dist: mayavi; extra == "mayavi"
Requires-Dist: mlabtex; extra == "mayavi"
Requires-Dist: vtk; extra == "mayavi"
Provides-Extra: plotly-static
Requires-Dist: kaleido; extra == "plotly-static"
Provides-Extra: smooth
Requires-Dist: PyMCubes; extra == "smooth"
Provides-Extra: strict
Requires-Dist: matplotlib==3.9.2; extra == "strict"
Requires-Dist: pymatgen==2024.8.9; extra == "strict"
Requires-Dist: BoltzTraP2==24.7.2; extra == "strict"
Requires-Dist: trimesh==4.4.8; extra == "strict"
Requires-Dist: meshcut==0.3.0; extra == "strict"
Requires-Dist: scikit-image==0.24.0; extra == "strict"
Requires-Dist: monty==2024.7.30; extra == "strict"
Requires-Dist: spglib==2.5.0; extra == "strict"
Requires-Dist: plotly==5.24.0; extra == "strict"
Requires-Dist: pyfftw==0.14.0; extra == "strict"
Requires-Dist: psutil==6.0.0; extra == "strict"
Requires-Dist: click==8.1.7; extra == "strict"
Requires-Dist: networkx==3.2.1; extra == "strict"
Requires-Dist: tabulate==0.9.0; extra == "strict"
Requires-Dist: numpy; extra == "strict"
Requires-Dist: scipy; extra == "strict"
Provides-Extra: tests
Requires-Dist: pytest==8.3.2; extra == "tests"
